risingwave/__init__.py
risingwave/core.py
risingwave_py-0.0.2.dist-info/METADATA
risingwave_py-0.0.2.dist-info/WHEEL
risingwave_py-0.0.2.dist-info/licenses/LICENSE
risingwave_py-0.0.2.dist-info/RECORD
