Metadata-Version: 2.4
Name: risingwave-py
Version: 0.0.2
Summary: Python SDK for real-time processing
Project-URL: Homepage, https://github.com/risingwavelabs/risingwave-py
Project-URL: Issues, https://github.com/risingwavelabs/risingwave-py/issues
Author-email: Mike Wang <mikecwangcn@gmail.com>, Patrick Huang <hzxa21@hotmail.com>
License-Expression: Apache-2.0
License-File: LICENSE
Keywords: risingwave,risingwave-py,risingwave-python,risingwave_py,risingwave_python
Classifier: Operating System :: OS Independent
Classifier: Programming Language :: Python :: 3
Requires-Python: >=3.9
Requires-Dist: pandas>=2.2.2
Requires-Dist: semver>=3.0.2
Requires-Dist: sqlalchemy-risingwave==1.1.1
